[{"word":"the","level":1},{"word":"2","level":1},{"word":"and","level":1},{"word":"he","level":1},{"word":"a","level":1},{"word":"i","level":1},{"word":"you","level":1},{"word":"it","level":1},{"word":"of","level":1},{"word":"in","level":1},{"word":"was","level":1},{"word":"said","level":1},{"word":"his","level":1},{"word":"that","level":1},{"word":"she","level":1},{"word":"4","level":1},{"word":"on","level":1},{"word":"they","level":1},{"word":"but","level":1},{"word":"had","level":1},{"word":"at","level":1},{"word":"him","level":1},{"word":"with","level":1},{"word":"up","level":1},{"word":"all","level":1},{"word":"look","level":2},{"word":"is","level":2},{"word":"her","level":2},{"word":"there","level":2},{"word":"some","level":2},{"word":"out","level":2},{"word":"as","level":2},{"word":"B","level":2},{"word":"have","level":2},{"word":"go","level":2},{"word":"we","level":2},{"word":"am","level":2},{"word":"then","level":2},{"word":"little","level":2},{"word":"down","level":2},{"word":"do","level":2},{"word":"can","level":2},{"word":"could","level":2},{"word":"when","level":2},{"word":"did","level":2},{"word":"what","level":2},{"word":"so","level":2},{"word":"see","level":2},{"word":"not","level":2},{"word":"wer","level":2},{"word":"get","level":3},{"word":"them","level":3},{"word":"like","level":3},{"word":"1","level":3},{"word":"this","level":3},{"word":"my","level":3},{"word":"wood","level":3},{"word":"me","level":3},{"word":"will","level":3},{"word":"yes","level":3},{"word":"big","level":3},{"word":"went","level":3},{"word":"AR","level":3},{"word":"come","level":3},{"word":"if","level":3},{"word":"now","level":3},{"word":"long","level":3},{"word":"no","level":3},{"word":"came","level":3},{"word":"ask","level":3},{"word":"very","level":3},{"word":"an","level":3},{"word":"over","level":3},{"word":"your","level":3},{"word":"it's","level":3},{"word":"ride","level":4},{"word":"into","level":4},{"word":"just","level":4},{"word":"blue","level":4},{"word":"red","level":4},{"word":"from","level":4},{"word":"good","level":4},{"word":"any","level":4},{"word":"about","level":4},{"word":"around","level":4},{"word":"want","level":4},{"word":"don't","level":4},{"word":"how","level":4},{"word":"no","level":4},{"word":"right","level":4},{"word":"put","level":4},{"word":"2","level":4},{"word":"got","level":4},{"word":"take","level":4},{"word":"where","level":4},{"word":"every","level":4},{"word":"pretty","level":4},{"word":"jump","level":4},{"word":"green","level":4},{"word":"4","level":4},{"word":"away","level":5},{"word":"old","level":5},{"word":"bye","level":5},{"word":"there","level":5},{"word":"here","level":5},{"word":"saw","level":5},{"word":"call","level":5},{"word":"after","level":5},{"word":"well","level":5},{"word":"think","level":5},{"word":"ran","level":5},{"word":"let","level":5},{"word":"help","level":5},{"word":"make","level":5},{"word":"going","level":5},{"word":"sleep","level":5},{"word":"Brown","level":5},{"word":"yellow","level":5},{"word":"5","level":5},{"word":"6","level":5},{"word":"walk","level":5},{"word":"2","level":5},{"word":"or","level":5},{"word":"before","level":5},{"word":"eat","level":5},{"word":"again","level":6},{"word":"Play","level":6},{"word":"Who","level":6},{"word":"been","level":6},{"word":"may","level":6},{"word":"stop","level":6},{"word":"off","level":6},{"word":"never","level":6},{"word":"7","level":6},{"word":"8","level":6},{"word":"cold","level":6},{"word":"today","level":6},{"word":"fly","level":6},{"word":"myself","level":6},{"word":"round","level":6},{"word":"tell","level":6},{"word":"much","level":6},{"word":"keep","level":6},{"word":"give","level":6},{"word":"work","level":6},{"word":"first","level":6},{"word":"try","level":6},{"word":"new","level":6},{"word":"must","level":6},{"word":"start","level":6},{"word":"black","level":7},{"word":"white","level":7},{"word":"10","level":7},{"word":"does","level":7},{"word":"bring","level":7},{"word":"goes","level":7},{"word":"right","level":7},{"word":"always","level":7},{"word":"drink","level":7},{"word":"once","level":7},{"word":"soon","level":7},{"word":"made","level":7},{"word":"run","level":7},{"word":"gave","level":7},{"word":"open","level":7},{"word":"has","level":7},{"word":"find","level":7},{"word":"only","level":7},{"word":"us","level":7},{"word":"3","level":7},{"word":"our","level":7},{"word":"better","level":7},{"word":"hold","level":7},{"word":"bye","level":7},{"word":"funny","level":7},{"word":"warm","level":8},{"word":"8","level":8},{"word":"full","level":8},{"word":"those","level":8},{"word":"done","level":8},{"word":"use","level":8},{"word":"fast","level":8},{"word":"say","level":8},{"word":"light","level":8},{"word":"pick","level":8},{"word":"hurt","level":8},{"word":"pull","level":8},{"word":"cut","level":8},{"word":"kind","level":8},{"word":"both","level":8},{"word":"sit","level":8},{"word":"which","level":8},{"word":"fall","level":8},{"word":"carry","level":8},{"word":"small","level":8},{"word":"under","level":8},{"word":"read","level":8},{"word":"why","level":8},{"word":"own","level":8},{"word":"found","level":8},{"word":"wash","level":9},{"word":"show","level":9},{"word":"hot","level":9},{"word":"because","level":9},{"word":"far","level":9},{"word":"live","level":9},{"word":"draw","level":9},{"word":"clean","level":9},{"word":"grow","level":9},{"word":"best","level":9},{"word":"upon","level":9},{"word":"these","level":9},{"word":"sing","level":9},{"word":"together","level":9},{"word":"please","level":9},{"word":"thank","level":9},{"word":"wish","level":9},{"word":"many","level":9},{"word":"shall","level":9},{"word":"laugh","level":9}]